mulfile/__init__.py
mulfile/gwyddion.py
mulfile/mul.py
mulfile/py.typed
mulfile-0.4.0.dist-info/LICENSE.rst
mulfile-0.4.0.dist-info/METADATA
mulfile-0.4.0.dist-info/WHEEL
mulfile-0.4.0.dist-info/RECORD
