Metadata-Version: 2.1
Name: mulfile
Version: 0.4.0
Summary: Python library to read .mul and .flm files
Home-page: https://github.com/matkrin/mulfile
License: BSD-3-Clause
Author: Matthias Krinninger
Author-email: matkrin@protonmail.com
Requires-Python: >=3.10
Classifier: Development Status :: 3 - Alpha
Classifier: Intended Audience :: Developers
Classifier: Intended Audience :: Science/Research
Classifier: License :: OSI Approved :: BSD License
Classifier: Operating System :: OS Independent
Classifier: Programming Language :: Python :: 3
Classifier: Programming Language :: Python :: 3.10
Classifier: Programming Language :: Python :: 3.11
Classifier: Programming Language :: Python :: 3.12
Classifier: Topic :: Scientific/Engineering
Requires-Dist: numpy (>=1.24)
